Metadata-Version: 1.0
Name: logi
Version: 1.3.4
Summary: a loging library
Home-page: https://github.com/hiikion/logi
Author: hiikion
Author-email: UNKNOWN
License: MPL-2.0 License
Platform: UNKNOWN
